lbr_testsuite/__init__.py
lbr_testsuite/_pytest_plugins/__init__.py
lbr_testsuite/_pytest_plugins/plugin.py
lbr_testsuite/_pytest_plugins/generators/__init__.py
lbr_testsuite/_pytest_plugins/generators/spirent/__init__.py
lbr_testsuite/_pytest_plugins/generators/spirent/plugin.py
lbr_testsuite/_pytest_plugins/hugepages/__init__.py
lbr_testsuite/_pytest_plugins/hugepages/plugin.py
lbr_testsuite/_pytest_plugins/keyboard_interrupt/__init__.py
lbr_testsuite/_pytest_plugins/keyboard_interrupt/plugin.py
lbr_testsuite/_pytest_plugins/machine_defaults/__init__.py
lbr_testsuite/_pytest_plugins/machine_defaults/plugin.py
lbr_testsuite/_pytest_plugins/profiling/__init__.py
lbr_testsuite/_pytest_plugins/profiling/plugin.py
lbr_testsuite/_pytest_plugins/renamer/__init__.py
lbr_testsuite/_pytest_plugins/renamer/plugin.py
lbr_testsuite/_pytest_plugins/throughput/__init__.py
lbr_testsuite/_pytest_plugins/throughput/plugin.py
lbr_testsuite/_pytest_plugins/topology/__init__.py
lbr_testsuite/_pytest_plugins/topology/_options.py
lbr_testsuite/_pytest_plugins/topology/_spirent.py
lbr_testsuite/_pytest_plugins/topology/_spirent_with_loopback.py
lbr_testsuite/_pytest_plugins/topology/_trex.py
lbr_testsuite/_pytest_plugins/topology/_virtual_devices.py
lbr_testsuite/_pytest_plugins/topology/_wired_loopback.py
lbr_testsuite/_pytest_plugins/topology/plugin.py
lbr_testsuite/_pytest_plugins/vlan_config/__init__.py
lbr_testsuite/_pytest_plugins/vlan_config/plugin.py
lbr_testsuite/_trex_imports/__init__.py
lbr_testsuite/_trex_imports/_deimport_scapy.py
lbr_testsuite/_trex_imports/_deimport_yaml.py
lbr_testsuite/_trex_imports/_preload_trex_scapy.py
lbr_testsuite/common/__init__.py
lbr_testsuite/common/common.py
lbr_testsuite/common/conv.py
lbr_testsuite/common/sysctl.py
lbr_testsuite/data_table/__init__.py
lbr_testsuite/data_table/benchmark_charts.py
lbr_testsuite/data_table/charts.py
lbr_testsuite/data_table/data_table.py
lbr_testsuite/data_table/line_colors.py
lbr_testsuite-6.1.0.dist-info/licenses/LICENSE
lbr_testsuite-6.1.0.dist-info/METADATA
lbr_testsuite-6.1.0.dist-info/WHEEL
lbr_testsuite-6.1.0.dist-info/entry_points.txt
lbr_testsuite-6.1.0.dist-info/top_level.txt
lbr_testsuite-6.1.0.dist-info/RECORD
