Metadata-Version: 2.4
Name: lbr_testsuite
Version: 6.1.0
Summary: Lbr_testsuite package contains various modules used by CESNET projects
Author-email: CESNET <tmc-info@cesnet.cz>
Maintainer-email: Jan Sobol <Jan.Sobol@cesnet.cz>, Pavel Krobot <Pavel.Krobot@cesnet.cz>, Dominik Tran <Dominik.Tran@cesnet.cz>
License: BSD-3-Clause
Project-URL: repository, https://github.com/CESNET/lbr-testsuite/
Classifier: Programming Language :: Python :: 3.11
Classifier: Framework :: Pytest
Requires-Python: >=3.9
License-File: LICENSE
Requires-Dist: pyroute2<0.9.0,>=0.6.2
Requires-Dist: lbr-trex-client==3.4.0.dev311
Requires-Dist: stcrestclient
Requires-Dist: pytest>=7.0
Requires-Dist: pytest-cases>=3.6.11
Requires-Dist: pytest-instafail
Requires-Dist: fabric>=3.0.0
Requires-Dist: faker
Requires-Dist: scapy
Requires-Dist: matplotlib
Requires-Dist: pandas
Requires-Dist: python-papi
Requires-Dist: psutil
Requires-Dist: pyJoules
Requires-Dist: plotly>=5.24.1
Dynamic: license-file
